mcp4modal_sandbox/__init__.py
mcp4modal_sandbox/__main__.py
mcp4modal_sandbox/log.py
mcp4modal_sandbox/settings.py
mcp4modal_sandbox/backend/mcp_metadata.py
mcp4modal_sandbox/backend/mcp_server.py
mcp4modal_sandbox/backend/response_schema.py
mcp4modal_sandbox/backend/tool_descriptions.py
mcp4modal_sandbox-1.0.0.dist-info/METADATA
mcp4modal_sandbox-1.0.0.dist-info/WHEEL
mcp4modal_sandbox-1.0.0.dist-info/entry_points.txt
mcp4modal_sandbox-1.0.0.dist-info/RECORD
