Metadata-Version: 2.4
Name: mcp4modal-sandbox
Version: 1.0.0
Summary: A powerful Model Context Protocol (MCP) server for seamless cloud-based sandbox management using Modal.com
Project-URL: Homepage, https://github.com/milkymap/mcp4modal_sandbox
Project-URL: Repository, https://github.com/milkymap/mcp4modal_sandbox
Project-URL: Documentation, https://github.com/milkymap/mcp4modal_sandbox#readme
Project-URL: Issues, https://github.com/milkymap/mcp4modal_sandbox/issues
Author-email: milkymap <ibrahima.elmokhtar@gmail.com>
Maintainer-email: milkymap <ibrahima.elmokhtar@gmail.com>
License-Expression: MIT
Keywords: ai,cloud,compute,gpu,llm,mcp,modal,sandbox
Classifier: Development Status :: 4 - Beta
Classifier: Intended Audience :: Developers
Classifier: License :: OSI Approved :: MIT License
Classifier: Programming Language :: Python :: 3
Classifier: Programming Language :: Python :: 3.12
Classifier: Topic :: Scientific/Engineering :: Artificial Intelligence
Classifier: Topic :: Software Development :: Libraries :: Python Modules
Classifier: Topic :: System :: Distributed Computing
Requires-Python: >=3.12
Requires-Dist: aiofiles>=24.1.0
Requires-Dist: click>=8.1.8
Requires-Dist: fastmcp>=2.6.1
Requires-Dist: mcp[cli]>=1.9.2
Requires-Dist: modal>=1.0.2
Requires-Dist: pydantic-settings>=2.9.1
Requires-Dist: python-dotenv>=1.0.0
Requires-Dist: pyzmq>=26.4.0
Requires-Dist: rich>=14.0.0
Requires-Dist: uvicorn>=0.34.3
